{
  "name": "alpine-dev",
  "image": "ghcr.io/romange/alpine-dev",
  "customizations": {
    "vscode": {
      "extensions": [
        "ms-vscode.cpptools",
        "ms-vscode.cmake-tools",
        "ms-vscode.cpptools-themes",
        "twxs.cmake"
      ],
      "settings": {
        "cmake.buildDirectory": "/build",
        "extensions.ignoreRecommendations": true,
        "cmake.configureArgs": []
      }
    }
  },
  "mounts": [
    "source=alpine-vol,target=/build,type=volume"
  ],
  "postCreateCommand": ".devcontainer/alpine/post-create.sh ${containerWorkspaceFolder}"
}
